mgcplotter/bin/Darwin/mmseqs
mgcplotter/bin/Linux/mmseqs
mgcplotter/circos_config.py
mgcplotter/circos_legend.py
mgcplotter/config.py
mgcplotter/etc/BREWER
mgcplotter/etc/README
mgcplotter/etc/background.black.conf
mgcplotter/etc/background.white.conf
mgcplotter/etc/brewer.all.conf
mgcplotter/etc/brewer.conf
mgcplotter/etc/colors.brewer.conf
mgcplotter/etc/colors.conf
mgcplotter/etc/colors.hsv.conf
mgcplotter/etc/colors.ucsc.conf
mgcplotter/etc/colors.unix.txt
mgcplotter/etc/colors_fonts_patterns.conf
mgcplotter/etc/fonts/modern/.uuid
mgcplotter/etc/fonts/modern/cmunbbx.ttf
mgcplotter/etc/fonts/modern/cmunbi.ttf
mgcplotter/etc/fonts/modern/cmunbl.ttf
mgcplotter/etc/fonts/modern/cmunbmo.ttf
mgcplotter/etc/fonts/modern/cmunbmr.ttf
mgcplotter/etc/fonts/modern/cmunbso.ttf
mgcplotter/etc/fonts/modern/cmunbsr.ttf
mgcplotter/etc/fonts/modern/cmunbtl.ttf
mgcplotter/etc/fonts/modern/cmunbto.ttf
mgcplotter/etc/fonts/modern/cmunbx.ttf
mgcplotter/etc/fonts/modern/cmunbxo.ttf
mgcplotter/etc/fonts/modern/cmunci.ttf
mgcplotter/etc/fonts/modern/cmunit.ttf
mgcplotter/etc/fonts/modern/cmunobi.ttf
mgcplotter/etc/fonts/modern/cmunobx.ttf
mgcplotter/etc/fonts/modern/cmunorm.ttf
mgcplotter/etc/fonts/modern/cmunoti.ttf
mgcplotter/etc/fonts/modern/cmunrb.ttf
mgcplotter/etc/fonts/modern/cmunrm.ttf
mgcplotter/etc/fonts/modern/cmunsi.ttf
mgcplotter/etc/fonts/modern/cmunsl.ttf
mgcplotter/etc/fonts/modern/cmunso.ttf
mgcplotter/etc/fonts/modern/cmunss.ttf
mgcplotter/etc/fonts/modern/cmunssdc.ttf
mgcplotter/etc/fonts/modern/cmunst.ttf
mgcplotter/etc/fonts/modern/cmunsx.ttf
mgcplotter/etc/fonts/modern/cmuntb.ttf
mgcplotter/etc/fonts/modern/cmunti.ttf
mgcplotter/etc/fonts/modern/cmuntt.ttf
mgcplotter/etc/fonts/modern/cmuntx.ttf
mgcplotter/etc/fonts/modern/cmunui.ttf
mgcplotter/etc/fonts/modern/cmunvi.ttf
mgcplotter/etc/fonts/modern/cmunvt.ttf
mgcplotter/etc/fonts.conf
mgcplotter/etc/gddiag.conf
mgcplotter/etc/housekeeping.conf
mgcplotter/etc/image.black.conf
mgcplotter/etc/image.conf
mgcplotter-1.0.1.dist-info/entry_points.txt
mgcplotter-1.0.1.dist-info/LICENSE
mgcplotter-1.0.1.dist-info/WHEEL
mgcplotter-1.0.1.dist-info/METADATA
mgcplotter-1.0.1.dist-info/RECORD
