Metadata-Version: 2.1
Name: mgcplotter
Version: 1.0.1
Summary: Microbial Genome Circular plotting tool using Circos
Home-page: https://github.com/moshi4/MGCplotter/
License: GPL-3.0-only
Keywords: bioinformatics,genomics,comparative-genomics,circos,visualization
Author: moshi
Requires-Python: >=3.8,<4.0
Classifier: Intended Audience :: Science/Research
Classifier: License :: OSI Approved :: GNU General Public License v3 (GPLv3)
Classifier: Programming Language :: Python :: 3
Classifier: Programming Language :: Python :: 3.10
Classifier: Programming Language :: Python :: 3.8
Classifier: Programming Language :: Python :: 3.9
Classifier: Topic :: Scientific/Engineering :: Bio-Informatics
Requires-Dist: biopython (>=1.79,<2.0)
Requires-Dist: cogclassifier (>=1.0.4,<2.0.0)
Requires-Dist: matplotlib (>=3.5.1,<4.0.0)
Requires-Dist: pandas (>=1.4.2,<2.0.0)
Project-URL: Repository, https://github.com/moshi4/MGCplotter/
